jupyterlab_smceservices/__init__.py
jupyterlab_smceservices/_version.py
jupyterlab_smceservices-0.1.7.data/data/etc/jupyter/jupyter_notebook_config.d/jupyterlab_smceservices.json
jupyterlab_smceservices-0.1.7.data/data/share/jupyter/labextensions/jupyterlab_smceservices/build_log.json
jupyterlab_smceservices-0.1.7.data/data/share/jupyter/labextensions/jupyterlab_smceservices/package.json
jupyterlab_smceservices-0.1.7.data/data/share/jupyter/labextensions/jupyterlab_smceservices/schemas/jupyterlab-smceservices/package.json.orig
jupyterlab_smceservices-0.1.7.data/data/share/jupyter/labextensions/jupyterlab_smceservices/schemas/jupyterlab-smceservices/plugin.json
jupyterlab_smceservices-0.1.7.data/data/share/jupyter/labextensions/jupyterlab_smceservices/static/lib_index_js.4c5488affcc51b6df141.js
jupyterlab_smceservices-0.1.7.data/data/share/jupyter/labextensions/jupyterlab_smceservices/static/lib_index_js.4c5488affcc51b6df141.js.map
jupyterlab_smceservices-0.1.7.data/data/share/jupyter/labextensions/jupyterlab_smceservices/static/remoteEntry.d6fc6950f64217a94f8c.js
jupyterlab_smceservices-0.1.7.data/data/share/jupyter/labextensions/jupyterlab_smceservices/static/remoteEntry.d6fc6950f64217a94f8c.js.map
jupyterlab_smceservices-0.1.7.data/data/share/jupyter/labextensions/jupyterlab_smceservices/static/style.js
jupyterlab_smceservices-0.1.7.data/data/share/jupyter/labextensions/jupyterlab_smceservices/static/style_index_css.160f7892e1c536297548.js
jupyterlab_smceservices-0.1.7.data/data/share/jupyter/labextensions/jupyterlab_smceservices/static/style_index_css.160f7892e1c536297548.js.map
jupyterlab_smceservices-0.1.7.data/data/share/jupyter/labextensions/jupyterlab_smceservices/install.json
jupyterlab_smceservices-0.1.7.dist-info/METADATA
jupyterlab_smceservices-0.1.7.dist-info/WHEEL
jupyterlab_smceservices-0.1.7.dist-info/licenses/LICENSE
jupyterlab_smceservices-0.1.7.dist-info/RECORD
