Metadata-Version: 2.1
Name: jupyterlab_smceservices
Version: 0.1.7
Summary: A JupyterLab extension to provide information the SMCE Services
Project-URL: Homepage, https://github.com/github_username/jupyterlab_smceservices
Project-URL: Bug Tracker, https://github.com/github_username/jupyterlab_smceservices/issues
Project-URL: Repository, https://github.com/github_username/jupyterlab_smceservices.git
Author-email: Navteca LLC <info@navteca.com>
License: BSD 3-Clause License
License-File: LICENSE
Classifier: Framework :: Jupyter
Classifier: Framework :: Jupyter :: JupyterLab
Classifier: Framework :: Jupyter :: JupyterLab :: 3
Classifier: Framework :: Jupyter :: JupyterLab :: Extensions
Classifier: Framework :: Jupyter :: JupyterLab :: Extensions :: Prebuilt
Classifier: License :: OSI Approved :: BSD License
Classifier: Programming Language :: Python
Classifier: Programming Language :: Python :: 3
Classifier: Programming Language :: Python :: 3.7
Classifier: Programming Language :: Python :: 3.8
Classifier: Programming Language :: Python :: 3.9
Classifier: Programming Language :: Python :: 3.10
Requires-Python: >=3.8
Requires-Dist: jupyter-server<3,>=2.0.1
Provides-Extra: test
